{
  "project_info": {
    "project_number": "377329867932",
    "project_id": "geography-682b7",
    "storage_bucket": "geography-682b7.firebasestorage.app"
  },
  "client": [
    {
      "client_info": {
        "mobilesdk_app_id": "1:377329867932:android:c5ea4f29468750f8a86159",
        "android_client_info": {
          "package_name": "com.example.geography_geyser"
        }
      },
      "oauth_client": [
        {
          "client_id": "377329867932-mes5rn144638hnn7cjhofaiuki1lt6pn.apps.googleusercontent.com",
          "client_type": 1,
          "android_info": {
            "package_name": "com.example.geography_geyser",
            "certificate_hash": "b6a57d1f50e209bde458107221234e7f688dfe35"
          }
        },
        {
          "client_id": "377329867932-b8bmk1d883nh74memeevuub0f9amnovk.apps.googleusercontent.com",
          "client_type": 3
        }
      ],
      "api_key": [
        {
          "current_key": "AIzaSyALIgwlbl6ta9sjU5K0TtIoEYJNLDOYZHA"
        }
      ],
      "services": {
        "appinvite_service": {
          "other_platform_oauth_client": [
            {
              "client_id": "377329867932-b8bmk1d883nh74memeevuub0f9amnovk.apps.googleusercontent.com",
              "client_type": 3
            }
          ]
        }
      }
    }
  ],
  "configuration_version": "1"
}